pdftoppt/__init__.py
pdftoppt/cli.py
pdftoppt/converter.py
pdftoppt-1.0.0.dist-info/licenses/LICENSE
pdftoppt-1.0.0.dist-info/METADATA
pdftoppt-1.0.0.dist-info/WHEEL
pdftoppt-1.0.0.dist-info/entry_points.txt
pdftoppt-1.0.0.dist-info/top_level.txt
pdftoppt-1.0.0.dist-info/RECORD
