Metadata-Version: 2.4
Name: pdftoppt
Version: 1.0.0
Summary: Advanced PDF to PowerPoint converter with high fidelity
Home-page: https://github.com/amitpanda007/pdftoppt
Author: Amit Panda
Author-email: Amit Panda <amitpanda007@gmail.com>
License-Expression: MIT
Project-URL: Homepage, https://github.com/amitpanda007/pdftoppt
Project-URL: Bug Reports, https://github.com/amitpanda007/pdftoppt/issues
Project-URL: Source Code, https://github.com/amitpanda007/pdftoppt
Project-URL: Documentation, https://github.com/amitpanda007/pdftoppt#readme
Keywords: pdf,powerpoint,converter,presentation,office
Classifier: Development Status :: 4 - Beta
Classifier: Intended Audience :: Developers
Classifier: Intended Audience :: End Users/Desktop
Classifier: Operating System :: OS Independent
Classifier: Programming Language :: Python :: 3
Classifier: Programming Language :: Python :: 3.7
Classifier: Programming Language :: Python :: 3.8
Classifier: Programming Language :: Python :: 3.9
Classifier: Programming Language :: Python :: 3.10
Classifier: Programming Language :: Python :: 3.11
Classifier: Topic :: Office/Business :: Office Suites
Classifier: Topic :: Multimedia :: Graphics :: Graphics Conversion
Classifier: Topic :: Software Development :: Libraries :: Python Modules
Requires-Python: >=3.7
License-File: LICENSE
Requires-Dist: PyMuPDF>=1.20.0
Requires-Dist: python-pptx>=0.6.18
Requires-Dist: Pillow>=8.0.0
Provides-Extra: dev
Requires-Dist: pytest>=6.0; extra == "dev"
Requires-Dist: pytest-cov>=2.0; extra == "dev"
Requires-Dist: black>=21.0; extra == "dev"
Requires-Dist: flake8>=3.8; extra == "dev"
Requires-Dist: mypy>=0.800; extra == "dev"
Dynamic: author
Dynamic: home-page
Dynamic: license-file
Dynamic: requires-python
